README.md
setup.py
share_secrets/__init__.py
share_secrets/share_secret.py
share_secrets.egg-info/PKG-INFO
share_secrets.egg-info/SOURCES.txt
share_secrets.egg-info/dependency_links.txt
share_secrets.egg-info/entry_points.txt
share_secrets.egg-info/top_level.txt