Metadata-Version: 2.1
Name: share-secrets
Version: 0.5
Summary: share secrets with ease.
Home-page: https://github.com/Anish-M-code/share_secrets
Author: Anish M
Author-email: aneesh25861@gmail.com
License: GPLv3
Keywords: Secret sharing,cryptography,student project
Platform: UNKNOWN
Classifier: Development Status :: 5 - Production/Stable
Classifier: Intended Audience :: Developers
Classifier: Topic :: Software Development
Classifier: License :: OSI Approved :: GNU General Public License v3 (GPLv3)
Classifier: Programming Language :: Python :: 3
Classifier: Intended Audience :: Developers
Classifier: Intended Audience :: Education
Classifier: Topic :: Security :: Cryptography
